README.md
pyproject.toml
mlir_tensorrt_jax/__init__.py
mlir_tensorrt_jax/libmlir-tensorrt-pjrt.so
mlir_tensorrt_jax/flashinfer/__init__.py
mlir_tensorrt_jax/flashinfer/decode.py
mlir_tensorrt_jax/flashinfer/gemm.py
mlir_tensorrt_jax/flashinfer/prefill.py
mlir_tensorrt_jax/flashinfer/utils.py
mlir_tensorrt_jax/mtrt_ops/__init__.py
mlir_tensorrt_jax/mtrt_ops/dequantize.py
mlir_tensorrt_jax/mtrt_ops/dynamic_quantize.py
mlir_tensorrt_jax/mtrt_ops/quantize.py
mlir_tensorrt_jax/mtrt_ops/utils.py
mlir_tensorrt_jax.libs/libcuda-0de2c34b.so.580.105.08
mlir_tensorrt_jax-0.4.4.dist-info/METADATA
mlir_tensorrt_jax-0.4.4.dist-info/WHEEL
mlir_tensorrt_jax-0.4.4.dist-info/entry_points.txt
mlir_tensorrt_jax-0.4.4.dist-info/top_level.txt
mlir_tensorrt_jax-0.4.4.dist-info/RECORD
