Metadata-Version: 2.4
Name: mlir_tensorrt_jax
Version: 0.4.4
Summary: The MLIR-TensorRT JAX plugin.
Classifier: Programming Language :: Python :: 3
Classifier: Operating System :: POSIX :: Linux
Classifier: License :: OSI Approved :: BSD License
Classifier: Intended Audience :: Developers
Classifier: Development Status :: 4 - Beta
Requires-Dist: apache-tvm-ffi<0.2.0,>=0.1.0
Requires-Dist: jax<=0.6.2,>=0.5.3
Provides-Extra: cu12
Requires-Dist: flashinfer-jit-cache==0.5.0rc3+cu129; extra == "cu12"
Requires-Dist: cuda-python<13.0; extra == "cu12"
Provides-Extra: cu13
Requires-Dist: flashinfer-jit-cache==0.5.0rc3+cu130; extra == "cu13"
Requires-Dist: cuda-python>=13.0; extra == "cu13"
